Metadata-Version: 2.1
Name: sap-python-automation
Version: 1.0
Summary: Pacote usado para automações no SAP GUI
Home-page: UNKNOWN
Author: Ygor Seiji
License: UNKNOWN
Platform: UNKNOWN
